{
    "id": "5105022008001",
    "province": "Bali",
    "regency": "Klungkung",
    "district": "Banjarangkan",
    "sub_district": "Aan",
    "ballot_number": "01",
    "realResult": {
        "candidate1": {
            "digit1": null,
            "digit2": null,
            "digit3": 3
        },
        "candidate2": {
            "digit1": 1,
            "digit2": 5,
            "digit3": 2
        },
        "candidate3": {
            "digit1": null,
            "digit2": 7,
            "digit3": 0
        }
    },
    "slicedImage": {
        "candidate1": {
            "digit1": null,
            "digit2": null,
            "digit3": "../code/fyp/data_election/digits/5105022008001/candidate1/digit3/Screenshot 2024-12-25 at 15.44.36.png"
        },
        "candidate2": {
            "digit1": "../code/fyp/data_election/digits/5105022008001/candidate2/digit1/Screenshot 2024-12-25 at 15.44.42.png",
            "digit2": "../code/fyp/data_election/digits/5105022008001/candidate2/digit2/Screenshot 2024-12-25 at 15.44.46.png",
            "digit3": "../code/fyp/data_election/digits/5105022008001/candidate2/digit3/Screenshot 2024-12-25 at 15.44.50.png"
        },
        "candidate3": {
            "digit1": null,
            "digit2": "../code/fyp/data_election/digits/5105022008001/candidate3/digit2/Screenshot 2024-12-25 at 15.44.56.png",
            "digit3": "../code/fyp/data_election/digits/5105022008001/candidate3/digit3/Screenshot 2024-12-25 at 15.45.07.png"
        }
    },
    "predictedResult": {
        "candidate1": {
            "digit1": null,
            "digit2": null,
            "digit3": 3
        },
        "candidate2": {
            "digit1": 1,
            "digit2": 3,
            "digit3": 3
        },
        "candidate3": {
            "digit1": null,
            "digit2": 3,
            "digit3": 3
        }
    }
}